{
  "run_date": "2025-10-16",
  "symbols": [
    "BTCUSDT",
    "ETHUSDT",
    "SOLUSDT"
  ],
  "results": [
    {
      "symbol": "BTCUSDT",
      "lgbm_path": "backend/data/models/2025-10-16/BTCUSDT/lgbm.pkl",
      "tft_path": "backend/data/models/2025-10-16/BTCUSDT/tft.pt",
      "lgbm_score": 0.24308333333333332,
      "tft_score": 0.52,
      "best_score": 0.52,
      "best_model": "TFT"
    },
    {
      "symbol": "ETHUSDT",
      "lgbm_path": "backend/data/models/2025-10-16/ETHUSDT/lgbm.pkl",
      "tft_path": "backend/data/models/2025-10-16/ETHUSDT/tft.pt",
      "lgbm_score": 0.2531111111111111,
      "tft_score": 0.52,
      "best_score": 0.52,
      "best_model": "TFT"
    },
    {
      "symbol": "SOLUSDT",
      "lgbm_path": "backend/data/models/2025-10-16/SOLUSDT/lgbm.pkl",
      "tft_path": "backend/data/models/2025-10-16/SOLUSDT/tft.pt",
      "lgbm_score": 0.25172222222222224,
      "tft_score": 0.52,
      "best_score": 0.52,
      "best_model": "TFT"
    }
  ],
  "global_best": {
    "symbol": "BTCUSDT",
    "model": "TFT",
    "score": 0.52
  }
}